cbr_user_data/__init__.py
cbr_user_data/fast_api/User_Data__Fast_API.py
cbr_user_data/fast_api/__init__.py
cbr_user_data/fast_api/models/Model__API__User__Add_File.py
cbr_user_data/fast_api/models/Model__API__User__Add_Folder.py
cbr_user_data/fast_api/models/Model__API__User__Rename_File.py
cbr_user_data/fast_api/models/Model__API__User__Rename_Folder.py
cbr_user_data/fast_api/models/Model__API__User__Update_File.py
cbr_user_data/fast_api/models/__init__.py
cbr_user_data/fast_api/routes/Routes__Info.py
cbr_user_data/fast_api/routes/Routes__User.py
cbr_user_data/fast_api/routes/Routes__User__Chats.py
cbr_user_data/fast_api/routes/Routes__User__File_System.py
cbr_user_data/fast_api/routes/Routes__User__File_To_LLMs.py
cbr_user_data/fast_api/routes/Routes__User__Notifications.py
cbr_user_data/fast_api/routes/Routes__User__Personas.py
cbr_user_data/fast_api/routes/Routes__User__Session.py
cbr_user_data/fast_api/routes/Routes__User__UI.py
cbr_user_data/fast_api/routes/__init__.py
cbr_user_data/lambdas/__init__.py
cbr_user_data/lambdas/handler.py
cbr_user_data/ui/UI__User__Menu.py
cbr_user_data/ui/__init__.py
cbr_user_data/ui/models/Model__UI__User__Menu.py
cbr_user_data/ui/models/Model__UI__User__Menu_Item.py
cbr_user_data/utils/Version.py
cbr_user_data/utils/__init__.py
cbr_user_data/version
cbr_user_data-0.2.37.dist-info/LICENSE
cbr_user_data-0.2.37.dist-info/METADATA
cbr_user_data-0.2.37.dist-info/WHEEL
cbr_user_data-0.2.37.dist-info/RECORD
