Metadata-Version: 2.3
Name: cbr_user_data
Version: 0.2.37
Summary: CBR - User Data
License: MIT
Author: Dinis Cruz
Author-email: dinis.cruz@owasp.org
Requires-Python: >=3.11,<4.0
Classifier: License :: OSI Approved :: MIT License
Classifier: Programming Language :: Python :: 3
Classifier: Programming Language :: Python :: 3.11
Classifier: Programming Language :: Python :: 3.12
Classifier: Programming Language :: Python :: 3.13
Requires-Dist: cbr-content
Requires-Dist: cbr-shared
Requires-Dist: httpx
Requires-Dist: mangum
Requires-Dist: osbot-aws
Requires-Dist: osbot-fast-api
Requires-Dist: uvicorn
Requires-Dist: websockets
Project-URL: Homepage, https://github.com/the-cyber-boardroom/cbr-user-data
Project-URL: Repository, https://github.com/the-cyber-boardroom/cbr-user-data
